setup.py
restable/__init__.py
restable/util.py
restable.egg-info/PKG-INFO
restable.egg-info/SOURCES.txt
restable.egg-info/dependency_links.txt
restable.egg-info/requires.txt
restable.egg-info/top_level.txt