Metadata-Version: 1.0
Name: restable
Version: 0.1
Summary: Configuration-driven REST client
Home-page: UNKNOWN
Author: Erick Peirson
Author-email: erick.peirson@asu.edu
License: GNU GPL 3
Platform: UNKNOWN
